pipa/utils.py
pipa_utils-0.0.1.dist-info/METADATA
pipa_utils-0.0.1.dist-info/WHEEL
pipa_utils-0.0.1.dist-info/top_level.txt
pipa_utils-0.0.1.dist-info/RECORD
